catbox/__init__.py
catbox/catbox.py
catbox/exceptions.py
catbox/helpers.py
catbox_uploader-2.7.dist-info/LICENSE
catbox_uploader-2.7.dist-info/METADATA
catbox_uploader-2.7.dist-info/WHEEL
catbox_uploader-2.7.dist-info/top_level.txt
catbox_uploader-2.7.dist-info/RECORD
