Metadata-Version: 2.1
Name: catbox_uploader
Version: 2.7
Summary: A simple Python library to upload files and URLs to Catbox.moe
Home-page: https://github.com/lunaticsm/catbox-uploader
Author: viendi
Author-email: viendii@gmail.com
Classifier: Programming Language :: Python :: 3
Classifier: License :: OSI Approved :: MIT License
Classifier: Operating System :: OS Independent
Requires-Python: >=3.6
License-File: LICENSE
Requires-Dist: requests
